[
  {
    "inputs": [],
    "name": "call",
    "outputs": [],
    "stateMutability": "nonpayable",
    "type": "function"
  },
  {
    "anonymous": false,
    "inputs": [
      {
        "indexed": true,
        "internalType": "address",
        "name": "caller",
        "type": "address"
      },
      {
        "indexed": false,
        "internalType": "uint256",
        "name": "addressCalls",
        "type": "uint256"
      }
    ],
    "name": "Call",
    "type": "event"
  },
  {
    "inputs": [
      {
        "internalType": "uint256",
        "name": "_data",
        "type": "uint256"
      }
    ],
    "name": "dataCall",
    "outputs": [],
    "stateMutability": "nonpayable",
    "type": "function"
  },
  {
    "anonymous": false,
    "inputs": [
      {
        "indexed": true,
        "internalType": "address",
        "name": "caller",
        "type": "address"
      },
      {
        "indexed": false,
        "internalType": "uint256",
        "name": "data",
        "type": "uint256"
      }
    ],
    "name": "DataCall",
    "type": "event"
  },
  {
    "anonymous": false,
    "inputs": [
      {
        "indexed": true,
        "internalType": "address",
        "name": "caller",
        "type": "address"
      },
      {
        "indexed": false,
        "internalType": "uint256",
        "name": "totalContractCalls",
        "type": "uint256"
      }
    ],
    "name": "TotalCounter",
    "type": "event"
  },
  {
    "inputs": [
      {
        "internalType": "address",
        "name": "",
        "type": "address"
      }
    ],
    "name": "callsNumber",
    "outputs": [
      {
        "internalType": "uint256",
        "name": "",
        "type": "uint256"
      }
    ],
    "stateMutability": "view",
    "type": "function"
  },
  {
    "inputs": [
      {
        "internalType": "address",
        "name": "",
        "type": "address"
      }
    ],
    "name": "data",
    "outputs": [
      {
        "internalType": "uint256",
        "name": "",
        "type": "uint256"
      }
    ],
    "stateMutability": "view",
    "type": "function"
  },
  {
    "inputs": [
      {
        "internalType": "address",
        "name": "_address",
        "type": "address"
      }
    ],
    "name": "getCallsNumber",
    "outputs": [
      {
        "internalType": "uint256",
        "name": "",
        "type": "uint256"
      }
    ],
    "stateMutability": "view",
    "type": "function"
  },
  {
    "inputs": [],
    "name": "getSenderAddress",
    "outputs": [
      {
        "internalType": "address",
        "name": "",
        "type": "address"
      }
    ],
    "stateMutability": "view",
    "type": "function"
  },
  {
    "inputs": [],
    "name": "totalCounter",
    "outputs": [
      {
        "internalType": "uint256",
        "name": "",
        "type": "uint256"
      }
    ],
    "stateMutability": "view",
    "type": "function"
  }
]
